TwitterImgUtil/GVision.py
TwitterImgUtil/__init__.py
TwitterImgUtil/selfFFMPEG.py
TwitterImgUtil/twitter.py
TwitterImgUtil-0.4.dist-info/METADATA
TwitterImgUtil-0.4.dist-info/RECORD
TwitterImgUtil-0.4.dist-info/WHEEL
TwitterImgUtil-0.4.dist-info/top_level.txt
