Metadata-Version: 2.1
Name: TwitterImgUtil
Version: 0.4
Summary: include twitter images grabbing, adding labels function
Home-page: https://github.com/BrefCool/TwitterImgUtil
Author: bref
Author-email: syx525@bu.edu
License: UNKNOWN
Platform: UNKNOWN
Classifier: Programming Language :: Python :: 3
Classifier: License :: OSI Approved :: MIT License
Requires-Dist: tweepy
Requires-Dist: Pillow
Requires-Dist: google-cloud-videointelligence
Requires-Dist: google-cloud-vision
